pwml/__init__.py
pwml/classifiers/__init__.py
pwml/classifiers/embedders.py
pwml/classifiers/features.py
pwml/classifiers/hierarchical.py
pwml/timeseries/__init__.py
pwml/timeseries/dataaugmentationhelpers.py
pwml/timeseries/prophethelpers.py
pwml/timeseries/visualizationhelpers.py
pwml/utilities/__init__.py
pwml/utilities/classificationhelpers.py
pwml/utilities/commonhelpers.py
pwml/utilities/filehelpers.py
pwml/utilities/graphichelpers.py
pwml/utilities/httphelpers.py
pwml/utilities/imagehelpers.py
pwml/utilities/mssqlhelpers.py
pwml/utilities/neptunehelpers.py
Pwml-0.9.9.dist-info/LICENSE
Pwml-0.9.9.dist-info/METADATA
Pwml-0.9.9.dist-info/WHEEL
Pwml-0.9.9.dist-info/top_level.txt
Pwml-0.9.9.dist-info/RECORD
